{
  "Update_Date": "2026-04-29 17:00:07",
  "USD": {
    "Alış": "45,0668",
    "Tür": "Döviz",
    "Satış": "45,0733",
    "Değişim": "%0,05"
  },
  "EUR": {
    "Alış": "52,8406",
    "Tür": "Döviz",
    "Satış": "52,8548",
    "Değişim": "%0,06"
  },
  "GBP": {
    "Alış": "60,9144",
    "Tür": "Döviz",
    "Satış": "60,9337",
    "Değişim": "%0,05"
  },
  "CHF": {
    "Alış": "56,9529",
    "Tür": "Döviz",
    "Satış": "56,9755",
    "Değişim": "%-0,20"
  },
  "CAD": {
    "Alış": "32,8955",
    "Tür": "Döviz",
    "Satış": "32,9074",
    "Değişim": "%-0,07"
  },
  "RUB": {
    "Alış": "0,5970",
    "Tür": "Döviz",
    "Satış": "0,6033",
    "Değişim": "%0,16"
  },
  "AED": {
    "Alış": "12,2676",
    "Tür": "Döviz",
    "Satış": "12,2771",
    "Değişim": "%0,07"
  },
  "AUD": {
    "Alış": "32,1281",
    "Tür": "Döviz",
    "Satış": "32,1418",
    "Değişim": "%-0,68"
  },
  "DKK": {
    "Alış": "7,0465",
    "Tür": "Döviz",
    "Satış": "7,0493",
    "Değişim": "%-0,19"
  },
  "SEK": {
    "Alış": "4,8434",
    "Tür": "Döviz",
    "Satış": "4,8466",
    "Değişim": "%-0,30"
  },
  "NOK": {
    "Alış": "4,8443",
    "Tür": "Döviz",
    "Satış": "4,8465",
    "Değişim": "%0,27"
  },
  "JPY": {
    "Alış": "0,2828",
    "Tür": "Döviz",
    "Satış": "0,2835",
    "Değişim": "%-0,39"
  },
  "KWD": {
    "Alış": "146,1483",
    "Tür": "Döviz",
    "Satış": "146,6489",
    "Değişim": "%-0,01"
  },
  "ZAR": {
    "Alış": "2,6981",
    "Tür": "Döviz",
    "Satış": "2,6995",
    "Değişim": "%-0,90"
  },
  "BHD": {
    "Alış": "119,3728",
    "Tür": "Döviz",
    "Satış": "119,3900",
    "Değişim": "%-0,03"
  },
  "LYD": {
    "Alış": "7,0962",
    "Tür": "Döviz",
    "Satış": "7,0973",
    "Değişim": "%0,03"
  },
  "SAR": {
    "Alış": "12,0020",
    "Tür": "Döviz",
    "Satış": "12,0319",
    "Değişim": "%0,06"
  },
  "IQD": {
    "Alış": "0,0344",
    "Tür": "Döviz",
    "Satış": "0,0344",
    "Değişim": "%0,01"
  },
  "ILS": {
    "Alış": "15,1633",
    "Tür": "Döviz",
    "Satış": "15,1655",
    "Değişim": "%-0,31"
  },
  "INR": {
    "Alış": "0,4752",
    "Tür": "Döviz",
    "Satış": "0,4753",
    "Değişim": "%-0,26"
  },
  "MXN": {
    "Alış": "2,5795",
    "Tür": "Döviz",
    "Satış": "2,5799",
    "Değişim": "%-0,42"
  },
  "HUF": {
    "Alış": "0,1444",
    "Tür": "Döviz",
    "Satış": "0,1444",
    "Değişim": "%-0,44"
  },
  "NZD": {
    "Alış": "26,3148",
    "Tür": "Döviz",
    "Satış": "26,3186",
    "Değişim": "%-0,74"
  },
  "BRL": {
    "Alış": "8,9753",
    "Tür": "Döviz",
    "Satış": "8,9766",
    "Değişim": "%-0,88"
  },
  "IDR": {
    "Alış": "0,0026",
    "Tür": "Döviz",
    "Satış": "0,0026",
    "Değişim": "%-0,64"
  },
  "CZK": {
    "Alış": "2,1595",
    "Tür": "Döviz",
    "Satış": "2,1598",
    "Değişim": "%-0,30"
  },
  "PLN": {
    "Alış": "12,3776",
    "Tür": "Döviz",
    "Satış": "12,3794",
    "Değişim": "%-0,34"
  },
  "RON": {
    "Alış": "10,3239",
    "Tür": "Döviz",
    "Satış": "10,3322",
    "Değişim": "%-0,26"
  },
  "CNY": {
    "Alış": "6,5861",
    "Tür": "Döviz",
    "Satış": "6,5878",
    "Değişim": "%0,02"
  },
  "ARS": {
    "Alış": "0,0322",
    "Tür": "Döviz",
    "Satış": "0,0322",
    "Değişim": "%0,51"
  },
  "ALL": {
    "Alış": "0,5511",
    "Tür": "Döviz",
    "Satış": "0,5512",
    "Değişim": "%-0,19"
  },
  "AZN": {
    "Alış": "26,5099",
    "Tür": "Döviz",
    "Satış": "26,5137",
    "Değişim": "%0,05"
  },
  "BAM": {
    "Alış": "26,9732",
    "Tür": "Döviz",
    "Satış": "26,9771",
    "Değişim": "%0,26"
  },
  "CLP": {
    "Alış": "0,0500",
    "Tür": "Döviz",
    "Satış": "0,0501",
    "Değişim": "%-1,22"
  },
  "COP": {
    "Alış": "0,0124",
    "Tür": "Döviz",
    "Satış": "0,0124",
    "Değişim": "%-0,55"
  },
  "CRC": {
    "Alış": "0,0991",
    "Tür": "Döviz",
    "Satış": "0,0991",
    "Değişim": "%0,06"
  },
  "DZD": {
    "Alış": "0,3399",
    "Tür": "Döviz",
    "Satış": "0,3399",
    "Değişim": "%-0,02"
  },
  "EGP": {
    "Alış": "0,8512",
    "Tür": "Döviz",
    "Satış": "0,8513",
    "Değişim": "%-0,18"
  },
  "HKD": {
    "Alış": "5,7507",
    "Tür": "Döviz",
    "Satış": "5,7515",
    "Değişim": "%0,03"
  },
  "ISK": {
    "Alış": "0,3668",
    "Tür": "Döviz",
    "Satış": "0,3669",
    "Değişim": "%-0,44"
  },
  "KRW": {
    "Alış": "0,0304",
    "Tür": "Döviz",
    "Satış": "0,0304",
    "Değişim": "%-0,72"
  },
  "KZT": {
    "Alış": "0,0973",
    "Tür": "Döviz",
    "Satış": "0,0973",
    "Değişim": "%-0,96"
  },
  "LBP": {
    "Alış": "0,0005",
    "Tür": "Döviz",
    "Satış": "0,0005",
    "Değişim": "%0,01"
  },
  "LKR": {
    "Alış": "0,1410",
    "Tür": "Döviz",
    "Satış": "0,1410",
    "Değişim": "%-0,14"
  },
  "MAD": {
    "Alış": "4,8682",
    "Tür": "Döviz",
    "Satış": "4,8689",
    "Değişim": "%0,01"
  },
  "MDL": {
    "Alış": "2,6324",
    "Tür": "Döviz",
    "Satış": "2,6328",
    "Değişim": "%0,51"
  },
  "MKD": {
    "Alış": "0,8553",
    "Tür": "Döviz",
    "Satış": "0,8554",
    "Değişim": "%0,07"
  },
  "MYR": {
    "Alış": "11,4033",
    "Tür": "Döviz",
    "Satış": "11,4049",
    "Değişim": "%0,04"
  },
  "OMR": {
    "Alış": "117,2088",
    "Tür": "Döviz",
    "Satış": "117,2257",
    "Değişim": "%0,05"
  },
  "PEN": {
    "Alış": "12,8249",
    "Tür": "Döviz",
    "Satış": "12,8268",
    "Değişim": "%0,10"
  },
  "PHP": {
    "Alış": "0,7309",
    "Tür": "Döviz",
    "Satış": "0,7310",
    "Değişim": "%-0,87"
  },
  "PKR": {
    "Alış": "0,1608",
    "Tür": "Döviz",
    "Satış": "0,1625",
    "Değişim": "%0,06"
  },
  "QAR": {
    "Alış": "11,9387",
    "Tür": "Döviz",
    "Satış": "12,8109",
    "Değişim": "%0,09"
  },
  "RSD": {
    "Alış": "0,4496",
    "Tür": "Döviz",
    "Satış": "0,4505",
    "Değişim": "%0,07"
  },
  "SGD": {
    "Alış": "35,2084",
    "Tür": "Döviz",
    "Satış": "35,2135",
    "Değişim": "%-0,20"
  },
  "SYP": {
    "Alış": "0,3902",
    "Tür": "Döviz",
    "Satış": "0,3902",
    "Değişim": "%0,05"
  },
  "THB": {
    "Alış": "1,3755",
    "Tür": "Döviz",
    "Satış": "1,3757",
    "Değişim": "%-0,74"
  },
  "TWD": {
    "Alış": "1,4244",
    "Tür": "Döviz",
    "Satış": "1,4246",
    "Değişim": "%-0,33"
  },
  "UAH": {
    "Alış": "1,0222",
    "Tür": "Döviz",
    "Satış": "1,0223",
    "Değişim": "%0,10"
  },
  "UYU": {
    "Alış": "1,1323",
    "Tür": "Döviz",
    "Satış": "1,1325",
    "Değişim": "%-0,83"
  },
  "GEL": {
    "Alış": "16,7224",
    "Tür": "Döviz",
    "Satış": "16,7248",
    "Değişim": "%-0,32"
  },
  "TND": {
    "Alış": "15,4444",
    "Tür": "Döviz",
    "Satış": "15,4466",
    "Değişim": "%-1,15"
  },
  "BGN": {
    "Alış": "26,9644",
    "Tür": "Döviz",
    "Satış": "27,2251",
    "Değişim": "%0,28"
  },
  "ons": {
    "Alış": "$4.523,45",
    "Tür": "Altın",
    "Satış": "$4.524,09",
    "Değişim": "%-1,56"
  },
  "gram-altin": {
    "Alış": "6.554,64",
    "Tür": "Altın",
    "Satış": "6.555,57",
    "Değişim": "%-1,51"
  },
  "gram-has-altin": {
    "Alış": "6.521,87",
    "Tür": "Altın",
    "Satış": "6.522,79",
    "Değişim": "%-1,51"
  },
  "ceyrek-altin": {
    "Alış": "10.516,73",
    "Tür": "Altın",
    "Satış": "10.758,96",
    "Değişim": "%-0,93"
  },
  "yarim-altin": {
    "Alış": "20.967,73",
    "Tür": "Altın",
    "Satış": "21.517,91",
    "Değişim": "%-0,93"
  },
  "tam-altin": {
    "Alış": "42.066,92",
    "Tür": "Altın",
    "Satış": "42.904,22",
    "Değişim": "%-0,93"
  },
  "cumhuriyet-altini": {
    "Alış": "43.437,00",
    "Tür": "Altın",
    "Satış": "44.107,00",
    "Değişim": "%-1,23"
  },
  "ata-altin": {
    "Alış": "43.381,52",
    "Tür": "Altın",
    "Satış": "44.483,52",
    "Değişim": "%-0,93"
  },
  "14-ayar-altin": {
    "Alış": "3.746,59",
    "Tür": "Altın",
    "Satış": "3.750,83",
    "Değişim": "%-0,93"
  },
  "18-ayar-altin": {
    "Alış": "4.798,26",
    "Tür": "Altın",
    "Satış": "4.803,69",
    "Değişim": "%-0,93"
  },
  "22-ayar-bilezik": {
    "Alış": "5.994,54",
    "Tür": "Altın",
    "Satış": "6.001,33",
    "Değişim": "%-0,93"
  },
  "ikibucuk-altin": {
    "Alış": "105.167,31",
    "Tür": "Altın",
    "Satış": "106.865,73",
    "Değişim": "%-0,93"
  },
  "besli-altin": {
    "Alış": "212.963,81",
    "Tür": "Altın",
    "Satış": "217.153,27",
    "Değişim": "%-0,93"
  },
  "gremse-altin": {
    "Alış": "105.167,31",
    "Tür": "Altın",
    "Satış": "107.589,57",
    "Değişim": "%-0,93"
  },
  "resat-altin": {
    "Alış": "43.381,52",
    "Tür": "Altın",
    "Satış": "44.483,52",
    "Değişim": "%-0,93"
  },
  "hamit-altin": {
    "Alış": "43.381,52",
    "Tür": "Altın",
    "Satış": "44.483,52",
    "Değişim": "%-0,93"
  },
  "gumus": {
    "Alış": "103,79",
    "Tür": "Altın",
    "Satış": "103,86",
    "Değişim": "%-1,91"
  },
  "gram-platin": {
    "Alış": "2.741,79",
    "Tür": "Altın",
    "Satış": "2.749,87",
    "Değişim": "%-2,51"
  },
  "gram-paladyum": {
    "Alış": "2.110,73",
    "Tür": "Altın",
    "Satış": "2.120,29",
    "Değişim": "%-0,39"
  }
}